taskara/__init__.py
taskara/agent.py
taskara/auth/default.py
taskara/auth/key.py
taskara/auth/provider.py
taskara/auth/transport.py
taskara/benchmark.py
taskara/cli/main.py
taskara/config.py
taskara/db/conn.py
taskara/db/models.py
taskara/db/redis_connection.py
taskara/env.py
taskara/flag.py
taskara/img.py
taskara/metrics.py
taskara/review.py
taskara/runtime/base.py
taskara/runtime/docker.py
taskara/runtime/kube.py
taskara/runtime/load.py
taskara/runtime/process.py
taskara/server/app.py
taskara/server/models.py
taskara/server/router/benchmarks.py
taskara/server/router/tasks.py
taskara/task.py
taskara/util.py
taskara-0.1.249.dist-info/LICENSE
taskara-0.1.249.dist-info/METADATA
taskara-0.1.249.dist-info/WHEEL
taskara-0.1.249.dist-info/entry_points.txt
taskara-0.1.249.dist-info/RECORD
