Metadata-Version: 2.1
Name: taskara
Version: 0.1.249
Summary: Task management for AI agents
License: MIT
Author: Patrick Barker
Author-email: patrickbarkerco@gmail.com
Requires-Python: >=3.10,<4.0
Classifier: License :: OSI Approved :: MIT License
Classifier: Programming Language :: Python :: 3
Classifier: Programming Language :: Python :: 3.10
Classifier: Programming Language :: Python :: 3.11
Classifier: Programming Language :: Python :: 3.12
Provides-Extra: all
Provides-Extra: cli
Provides-Extra: runtime
Requires-Dist: agentcore (>=0.1.3,<0.2.0)
Requires-Dist: cryptography (>=43.0.1,<44.0.0)
Requires-Dist: docker (>=7.0.0,<8.0.0) ; extra == "runtime" or extra == "all"
Requires-Dist: google-auth (>=2.29.0,<3.0.0) ; extra == "runtime" or extra == "all"
Requires-Dist: google-cloud-container (>=2.45.0,<3.0.0) ; extra == "runtime" or extra == "all"
Requires-Dist: kubernetes (>=29.0.0,<30.0.0) ; extra == "runtime" or extra == "all"
Requires-Dist: namesgenerator (>=0.3,<0.4)
Requires-Dist: openmeter (>=1.0.0b188,<2.0.0)
Requires-Dist: pydantic (>=2.6.4,<3.0.0)
Requires-Dist: redis (>=5.2.0,<6.0.0)
Requires-Dist: shortuuid (>=1.0.13,<2.0.0)
Requires-Dist: skillpacks (>=0.1.128,<0.2.0)
Requires-Dist: sqlalchemy (>=2.0.29,<3.0.0)
Requires-Dist: tabulate (>=0.9.0,<0.10.0) ; extra == "cli" or extra == "all"
Requires-Dist: tqdm (>=4.66.4,<5.0.0)
Requires-Dist: typer (>=0.12.3,<0.13.0) ; extra == "cli" or extra == "all"
